kdl/__init__.py
kdl/cli.py
kdl/converters.py
kdl/errors.py
kdl/parsefuncs.py
kdl/parsing.py
kdl/printing.py
kdl/py.typed
kdl/result.py
kdl/stream.py
kdl/t.py
kdl/types.py
tests/__init__.py
tests/run.py
kdl_py-1.1.7.dist-info/LICENSE
kdl_py-1.1.7.dist-info/METADATA
kdl_py-1.1.7.dist-info/WHEEL
kdl_py-1.1.7.dist-info/entry_points.txt
kdl_py-1.1.7.dist-info/top_level.txt
kdl_py-1.1.7.dist-info/RECORD
