Metadata-Version: 2.1
Name: kdl-py
Version: 1.1.7
Summary: A parser for the KDL language.
Home-page: https://github.com/tabatkins/kdlpy/
Author: Tab Atkins-Bittner
Classifier: Development Status :: 5 - Production/Stable
Classifier: License :: OSI Approved :: MIT License
Classifier: Operating System :: OS Independent
Classifier: Programming Language :: Python :: 3.7
Classifier: Topic :: Software Development :: Documentation
Requires-Python: >=3.7
License-File: LICENSE
